MANIFEST.in
setup.cfg
setup.py
abel_airflow.egg-info/PKG-INFO
abel_airflow.egg-info/SOURCES.txt
abel_airflow.egg-info/dependency_links.txt
abel_airflow.egg-info/not-zip-safe
abel_airflow.egg-info/requires.txt
abel_airflow.egg-info/top_level.txt
airflow/__init__.py
airflow/alembic.ini
airflow/configuration.py
airflow/default_login.py
airflow/exceptions.py
airflow/jobs.py
airflow/minihivecluster.py
airflow/models.py
airflow/plugins_manager.py
airflow/settings.py
airflow/bin/__init__.py
airflow/bin/airflow
airflow/bin/cli.py
airflow/contrib/__init__.py
airflow/contrib/auth/__init__.py
airflow/contrib/auth/backends/__init__.py
airflow/contrib/auth/backends/github_enterprise_auth.py
airflow/contrib/auth/backends/google_auth.py
airflow/contrib/auth/backends/kerberos_auth.py
airflow/contrib/auth/backends/ldap_auth.py
airflow/contrib/auth/backends/password_auth.py
airflow/contrib/executors/__init__.py
airflow/contrib/executors/mesos_executor.py
airflow/contrib/hooks/__init__.py
airflow/contrib/hooks/aws_hook.py
airflow/contrib/hooks/bigquery_hook.py
airflow/contrib/hooks/cloudant_hook.py
airflow/contrib/hooks/datastore_hook.py
airflow/contrib/hooks/emr_hook.py
airflow/contrib/hooks/fs_hook.py
airflow/contrib/hooks/ftp_hook.py
airflow/contrib/hooks/gcp_api_base_hook.py
airflow/contrib/hooks/gcp_dataflow_hook.py
airflow/contrib/hooks/gcp_dataproc_hook.py
airflow/contrib/hooks/gcs_hook.py
airflow/contrib/hooks/qubole_hook.py
airflow/contrib/hooks/spark_sql_hook.py
airflow/contrib/hooks/sqoop_hook.py
airflow/contrib/hooks/ssh_hook.py
airflow/contrib/hooks/vertica_hook.py
airflow/contrib/operators/__init__.py
airflow/contrib/operators/bigquery_check_operator.py
airflow/contrib/operators/bigquery_operator.py
airflow/contrib/operators/bigquery_to_bigquery.py
airflow/contrib/operators/bigquery_to_gcs.py
airflow/contrib/operators/dataflow_operator.py
airflow/contrib/operators/dataproc_operator.py
airflow/contrib/operators/emr_add_steps_operator.py
airflow/contrib/operators/emr_create_job_flow_operator.py
airflow/contrib/operators/emr_terminate_job_flow_operator.py
airflow/contrib/operators/file_to_gcs.py
airflow/contrib/operators/fs_operator.py
