Metadata-Version: 1.1
Name: abel-airflow
Version: 1.7.1.3.post3
Summary: Programmatically author, schedule and monitor data pipelines
Home-page: https://github.com/apache/incubator-airflow
Author: Maxime Beauchemin
Author-email: maximebeauchemin@gmail.com
License: Apache License 2.0
Download-URL: https://github.com/apache/incubator-airflow/tarball/1.7.1.3-3
Platform: UNKNOWN
Classifier: Development Status :: 5 - Production/Stable
Classifier: Environment :: Console
Classifier: Environment :: Web Environment
Classifier: Intended Audience :: Developers
Classifier: Intended Audience :: System Administrators
Classifier: License :: OSI Approved :: Apache Software License
Classifier: Programming Language :: Python :: 2.7
Classifier: Programming Language :: Python :: 3.4
Classifier: Topic :: System :: Monitoring
